libpitlakq/__init__.py
libpitlakq/w2_fortran.cpython-313-darwin.so
libpitlakq-0.2.0.dist-info/METADATA
libpitlakq-0.2.0.dist-info/WHEEL
libpitlakq-0.2.0.dist-info/top_level.txt
libpitlakq-0.2.0.dist-info/RECORD
