Metadata-Version: 2.4
Name: libpitlakq
Version: 0.2.0
Summary: Compiled Fortan code of CE-QUAL-W2 for PITLAKQ
Author-email: Mike Müller <mmueller@hydrocomputing.com>
License: BSD-3-Clause
Project-URL: homepage, https://gitlab.com/hydrocomputing/libpitlakq
Project-URL: repository, https://githlab.com/hydrocomputing/libpitlakq
Project-URL: documentation, https://libpitlakq.readthedocs.io
Classifier: Development Status :: 5 - Production/Stable
